Metadata-Version: 1.0
Name: colup
Version: 0.1.1
Summary: Colup
Home-page: https://github.com/yNoah-droid/colobyv1.0
Author: Noah Okoh
Author-email: noahtochukwu10@gmail.com
License: UNKNOWN
Platform: UNKNOWN
